fnway/__init__.py
fnway/core.py
fnway-0.1.0.dist-info/LICENSE
fnway-0.1.0.dist-info/METADATA
fnway-0.1.0.dist-info/WHEEL
fnway-0.1.0.dist-info/top_level.txt
fnway-0.1.0.dist-info/RECORD
