Metadata-Version: 2.1
Name: fnway
Version: 0.1.0
Summary: Utilities for functional programming
Home-page: https://github.com/dferens/fnway
Author: Dmitriy Ferens
Author-email: ferensdima@gmail.com
License: UNKNOWN
Platform: UNKNOWN
Classifier: Development Status :: 3 - Alpha
Classifier: License :: OSI Approved :: MIT License
Classifier: Operating System :: OS Independent
Classifier: Programming Language :: Python :: 3.5
Classifier: Programming Language :: Python :: 3.6
Classifier: Programming Language :: Python :: 3.7
Classifier: Programming Language :: Python :: 3.8
Classifier: Programming Language :: Python :: 3.9
Requires-Python: >=3.5
Requires-Dist: frozendict (<2)
